kiwitcms-6.6.dist-info/DESCRIPTION.rst
kiwitcms-6.6.dist-info/METADATA
kiwitcms-6.6.dist-info/RECORD
kiwitcms-6.6.dist-info/WHEEL
kiwitcms-6.6.dist-info/metadata.json
kiwitcms-6.6.dist-info/top_level.txt
tcms/__init__.py
tcms/signals.py
tcms/urls.py
tcms/wsgi.py
tcms/core/__init__.py
tcms/core/admin.py
tcms/core/ajax.py
tcms/core/context_processors.py
tcms/core/history.py
tcms/core/middleware.py
tcms/core/serializer.py
tcms/core/views.py
tcms/core/widgets.py
tcms/core/contrib/__init__.py
tcms/core/contrib/comments/__init__.py
tcms/core/contrib/comments/apps.py
tcms/core/contrib/comments/forms.py
tcms/core/contrib/comments/utils.py
tcms/core/contrib/comments/views.py
tcms/core/contrib/linkreference/__init__.py
tcms/core/contrib/linkreference/forms.py
tcms/core/contrib/linkreference/models.py
tcms/core/contrib/linkreference/tests.py
tcms/core/contrib/linkreference/views.py
tcms/core/contrib/linkreference/migrations/0001_squashed.py
tcms/core/contrib/linkreference/migrations/__init__.py
tcms/core/forms/__init__.py
tcms/core/forms/fields.py
tcms/core/helpers/__init__.py
tcms/core/helpers/comments.py
tcms/core/migrations/0001_squashed.py
tcms/core/migrations/__init__.py
tcms/core/models/__init__.py
tcms/core/models/base.py
tcms/core/templatetags/__init__.py
tcms/core/templatetags/extra_filters.py
tcms/core/templatetags/report_tags.py
tcms/core/utils/__init__.py
tcms/core/utils/mailto.py
tcms/core/utils/validations.py
tcms/issuetracker/__init__.py
tcms/issuetracker/bugzilla_integration.py
tcms/issuetracker/github_integration.py
tcms/issuetracker/gitlab_integration.py
tcms/issuetracker/jira_integration.py
tcms/issuetracker/types.py
tcms/kiwi_auth/__init__.py
tcms/kiwi_auth/admin.py
tcms/kiwi_auth/forms.py
tcms/kiwi_auth/models.py
tcms/kiwi_auth/test_admin.py
tcms/kiwi_auth/test_profiles.py
tcms/kiwi_auth/tests.py
tcms/kiwi_auth/urls.py
tcms/kiwi_auth/views.py
tcms/kiwi_auth/migrations/0001_initial.py
tcms/kiwi_auth/migrations/__init__.py
tcms/locale/de_DE/LC_MESSAGES/django.mo
tcms/locale/de_DE/LC_MESSAGES/django.po
tcms/locale/en/LC_MESSAGES/django.mo
tcms/locale/en/LC_MESSAGES/django.po
