Metadata-Version: 2.0
Name: kiwitcms
Version: 6.6
Summary: Test Case Management System
Home-page: https://github.com/kiwitcms/Kiwi/
Maintainer: Kiwi TCMS
Maintainer-email: info@kiwitcms.org
License: GPLv2+
Keywords: test case
Platform: UNKNOWN
Classifier: Intended Audience :: Developers
Classifier: License :: OSI Approved :: GNU General Public License v2 or later (GPLv2+)
Classifier: Programming Language :: Python :: 3
Classifier: Programming Language :: Python :: 3.6
Classifier: Topic :: Software Development :: Quality Assurance
Classifier: Topic :: Software Development :: Testing
Requires-Dist: Django (==2.1.7)
Requires-Dist: Markdown (==3.0.1)
Requires-Dist: PyGithub (==1.43.5)
Requires-Dist: bleach (==3.1.0)
Requires-Dist: bleach-whitelist (==0.0.9)
Requires-Dist: django-attachments (>=1.3)
Requires-Dist: django-contrib-comments (==1.9.1)
Requires-Dist: django-glrm (==1.1.3)
Requires-Dist: django-grappelli (==2.12.2)
Requires-Dist: django-modern-rpc (==0.11.1)
Requires-Dist: django-simple-history (==2.7.0)
Requires-Dist: django-uuslug (==1.1.8)
Requires-Dist: django-vinaigrette (==1.2.0)
Requires-Dist: jira (==2.0.0)
Requires-Dist: python-bugzilla (==2.2.0)
Requires-Dist: python-gitlab (==1.8.0)
